tegridymidi/__init__.py
tegridymidi/bits_and_ints.py
tegridymidi/chords.py
tegridymidi/constants.py
tegridymidi/files_helpers.py
tegridymidi/haystack_search.py
tegridymidi/helpers.py
tegridymidi/karaoke.py
tegridymidi/matrixes.py
tegridymidi/melodies.py
tegridymidi/midi_to_colab_audio.py
tegridymidi/misc.py
tegridymidi/plots.py
tegridymidi/processors.py
tegridymidi/sample_midis_helpers.py
tegridymidi/tokenizers.py
tegridymidi/x_transformer.py
tegridymidi/examples/README.md
tegridymidi/legacy/MIDI.py
tegridymidi/legacy/TMELODIES.py
tegridymidi/legacy/TMIDIX.py
tegridymidi/legacy/TPLOTS.py
tegridymidi/legacy/__init__.py
tegridymidi/sample_midis/README.md
tegridymidi/sample_midis/seed-lyrics.mid
tegridymidi/sample_midis/seed-melody-harmonized.mid
tegridymidi/sample_midis/seed-melody.mid
tegridymidi/sample_midis/seed.mid
tegridymidi/sample_midis/seed2.mid
tegridymidi/sample_midis/seed3.mid
tegridymidi-24.9.8.dist-info/LICENSE
tegridymidi-24.9.8.dist-info/METADATA
tegridymidi-24.9.8.dist-info/WHEEL
tegridymidi-24.9.8.dist-info/top_level.txt
tegridymidi-24.9.8.dist-info/RECORD
